{
	"_MetaData_": {
		"StartPartKey": "Prolog_Rogue",
        "MapScene": "res://Scenes/Maps/StoryMaps/2_Cross_Road/crossroad_dialog_map.tscn"
	},
	"Prolog_Rogue":{
		"_NextPartKey": "Intro_WalkIn",
		"WaitForNextButton": false,
		"Inital_BlackOutState":"Black",
		"Blocks":[
			{
				"BlockType": "Blackout",
				"BlackOutState":"Black"
			},
			{
				"BlockType": "SpeechBox",
				"WaitToFinish": true,
				"WaitForNextButton": true,
				"Entries": [
					{
						"EntryType":"Clear"
					},
					{
						"EntryType":"Text",
						"Text": "Now Imagine a cutscene at @Color:Red@The Port@Clear@ where a @Color:Red@Rogue@Clear@ is running for thier life. "
					},
					{
						"EntryType":"WaitToRead"
					},
					{
						"EntryType":"Text",
						"Text": "They jump into a crate to hide, ",
						"NewLine": false
					},
					{
						"EntryType":"WaitToRead"
					},{
						"EntryType":"Text",
						"Text": "but are sealed in and loaded onto a boat. ",
						"NewLine": false
					},
					{
						"EntryType":"WaitToRead"
					},
					{
						"EntryType":"Text",
						"Text": "*Scene Ends*",
						"NewLine": true
					}
				]
			},
			{
				"BlockType": "SpeechBox",
				"WaitToFinish": true,
				"WaitForNextButton": false,
				"Entries": [
					{
						"EntryType":"Clear"
					},
					{
						"EntryType":"Hide"
					}
				]
			}
		]
	},
	"Intro_WalkIn":{
		"_NextPartKey": "Dialog1",
		"WaitForNextButton": true,
		"Inital_BlackOutState":"Black",
		"#EnsurePoses": {
			"Player1":"P1",
			"MysteriousFigure":"M1"
		},
		"Blocks":[
			{
				"BlockType": "Blackout",
				"BlackOutState":"Black"
			},
            {
                "BlockType": "Blackout",
                "WaitToFinish": false,
                "BlackOutState":"FadeIn"
            },
            {
                "BlockType": "MoveActor",
                "WaitToFinish": false,
                "TargetActorId": "Player1",
                "PathMarkerName": "P1",
                "FollowActor": true,
                "SpeedScale": 1
            },
            {
                "BlockType": "MoveActor",
                "WaitToFinish": false,
                "TargetActorId": "MysteriousFigure",
                "PathMarkerName": "M1",
                "FollowActor": false,
                "SpeedScale": 1
            },
            {
                "BlockType": "MoveActor",
                "WaitToFinish": false,
                "Loop": true,
                "TargetActorId": "BanditArcher_1",
                "PathMarkerName": "Arch1_L",
                "FollowActor": false,
                "SpeedScale": 1
            },
            {
                "BlockType": "MoveActor",
                "WaitToFinish": false,
                "Loop": true,
                "TargetActorId": "BanditArcher_2",
                "PathMarkerName": "Arch2_L",
                "FollowActor": false,
                "SpeedScale": 1
            },
            {
                "BlockType": "MoveActor",
                "WaitToFinish": false,
                "Loop": true,
                "TargetActorId": "BanditArmored_1",
                "PathMarkerName": "Band1_L",
                "FollowActor": false,
                "SpeedScale": 1
            },
            {
                "BlockType": "MoveActor",
                "WaitToFinish": false,
                "Loop": true,
                "TargetActorId": "BanditArmored_2",
                "PathMarkerName": "Band2",
                "FollowActor": false,
                "SpeedScale": 1
            },
            {
                "BlockType": "MoveActor",
                "WaitToFinish": false,
                "Loop": true,
                "TargetActorId": "BanditArmored_3",
                "PathMarkerName": "Band3",
                "FollowActor": false,
                "SpeedScale": 1
            },
            {
                "BlockType": "MoveActor",
                "WaitToFinish": false,
                "Loop": true,
                "TargetActorId": "BanditCaptain",
                "PathMarkerName": "Cpt1",
                "FollowActor": false,
                "SpeedScale": 1
            },

			{
				"BlockType": "PopUp",
				"WaitToFinish": false,
				"Create":"LocationTime",
				"PopUpType": "LocationTime",
				"Location": "The Crossroad",
				"Time": "3 months later"
			},
			{
				"BlockType": "Delay",
				"Time": 2.5
			},
            
			{
				"BlockType": "SpeechBox",
				"WaitToFinish": true,
				"Entries": [
					{
						"EntryType":"Clear"
					},
					{
						"EntryType":"Text",
						"Text": "As the @Color:Blue@The Party@Clear@ is making thier way to @Color:Red@The City@Clear@, they reach @Color:Red@The Crossroad@Clear@ and find a troubling sight. ",
                        "LetterDelay":0.015
					},
					{
						"EntryType":"WaitToRead"
					}
				]
            },
			{
				"WaitToFinish": false,
				"WaitForNextButton": false,
				"BlockType": "PanCamera",
				"TargetType": "PathMarker",
				"PathMarkerName": "C1"
			},
			{
				"BlockType": "SpeechBox",
				"WaitToFinish": true,
				"Entries": [
					{
						"EntryType":"Text",
						"Text": "A group of @Color:Red@Bandits@Clear@ are unpacking a seeming abondoned @Color:Red@Merchant Cart@Clear@.",
                        "LetterDelay":0.015,
                        "NewLine": false
					},
					{
						"EntryType":"WaitToRead"
					}
				]
            }
		]
	},
	"Dialog1":{
		"_NextPartKey": "Dialog2",
		"WaitForNextButton": true,
		"#EnsurePoses": {
			"Player1":"P1",
			"MysteriousFigure":"M1"
		},
		"Blocks":[
			{
				"BlockType": "SpeechBox",
				"WaitToFinish": true,
				"WaitForNextButton": true,
				"Entries": [ 
                    {
                        "EntryType": "Clear"
                    },
					{
						"EntryType": "Speaker",
						"SpeakerName": "MtFr",
						"SpeakerPort": "res://defs/Actors/NPCs/MnFg/Sprites/Portraits/MysFig_Neutral.png"
					},
					{
						"EntryType": "Text",
						"Text": "I'm going to guess that the \"@Color:Red@Merhant@Clear@\" @Color:Red@Cart@Clear@, doesn't belong to these \"@Color:Red@Bandits@Clear@\", "
					},
					{
						"EntryType":"WaitToRead"
					},
					{
						"EntryType": "Speaker",
						"SpeakerName": "MtFr",
						"SpeakerPort": "res://defs/Actors/NPCs/MnFg/Sprites/Portraits/MysFig_Squint.png"
					},
					{
						"EntryType": "Text",
						"Text": "which means",
						"NewLine": false
					},
                    
					{
						"EntryType": "Text",
						"Text": "... ",
						"LetterDelay": 0.1
					},
					{
						"EntryType": "Delay",
                        "Delay": 0.5
					},
					{
						"EntryType": "Speaker",
						"SpeakerName": "MtFr",
						"SpeakerPort": "res://defs/Actors/NPCs/MnFg/Sprites/Portraits/MysFig_Surprize.png"
					},
					{
						"EntryType": "Text",
						"Text": "this is a robbery!"
					}
                ]
            },
			{
				"BlockType": "SpeechBox",
				"WaitToFinish": true,
				"WaitForNextButton": true,
				"Entries": [ 
                    {
                        "EntryType": "Clear",
                        "ClearSpeaker": false
                    },
					{
						"EntryType": "Speaker",
						"SpeakerName": "MtFr",
						"SpeakerPort": "res://defs/Actors/NPCs/MnFg/Sprites/Portraits/MysFig_Sad.png"
					},
					{
						"EntryType": "Text",
						"Text": "If only we had gotten here first, ",
						"NewLine": true
					},
					{
						"EntryType":"WaitToRead"
					},
					{
						"EntryType": "Text",
						"Text": "then we could have stolen everything for oursevles.",
						"NewLine": false
					},
					{
						"EntryType":"WaitToRead"
					},
					{
						"EntryType": "Speaker",
						"SpeakerName": "MtFr",
						"SpeakerPort": "res://defs/Actors/NPCs/MnFg/Sprites/Portraits/MysFig_Happy.png"
					},
					{
						"EntryType": "Text",
						"Text": "But now we can get some Hero Points by killing these guys!",
						"NewLine": true
					},
					{
						"EntryType":"WaitToRead"
					}
				]
            },
            {
                "BlockType": "MoveActor",
                "WaitToFinish": false,
                "TargetActorId": "BanditCaptain",
                "PathMarkerName": "Cpt2",
                "FollowActor": false,
                "SpeedScale": 1.4
            },
            {
                "BlockType": "MoveActor",
                "WaitToFinish": false,
                "TargetActorId": "BanditArmored_3",
                "PathMarkerName": "Band3_2",
                "FollowActor": false,
                "SpeedScale": 1.4
            },
			{
				"BlockType": "SpeechBox",
				"WaitToFinish": false,
				"WaitForNextButton": false,
                "Hide": true,
				"Entries": [ 
                    {
                        "EntryType": "Clear",
                        "ClearSpeaker": false
                    }
				]
            },
			{
				"BlockType":"Delay",
				"Time": 1
			},
			{
				"BlockType": "SpeechBox",
				"WaitToFinish": false,
				"WaitForNextButton": false,
				"Entries": [ 
                    {
                        "EntryType": "Clear",
                        "ClearSpeaker": false
                    },
					{
						"EntryType": "Speaker",
						"SpeakerName": "MtFr",
						"SpeakerPort": "res://defs/Actors/NPCs/MnFg/Sprites/Portraits/MysFig_Neutral.png"
					},
					{
						"EntryType": "Text",
						"Text": "By the way, \"Hero Points\" aren't a thing.",
						"NewLine": true
					},
                    {
                        "EntryType":"WaitToRead"
                    },
					{
						"EntryType": "Text",
						"Text": "That was a figure of speech.",
						"NewLine": true
					},
                    {
                        "EntryType": "Delay",
                         "Delay": 2.0
                    },
                    {
                        "EntryType": "Hide"
                    }
				]
            },
            {
                "BlockType": "MoveActor",
                "WaitToFinish": true,
                "TargetActorId": "BanditArmored_3",
                "PathMarkerName": "Band3_CP",
                "FollowActor": false,
                "SpeedScale": 1.4
            },


			{
				"BlockType": "SpeechBox",
				"WaitToFinish": true,
				"WaitForNextButton": false,
				"TopBox": false,
                "Hide": true,
				"Entries": [ 
                    {
                        "EntryType": "Clear"
                    }
				]
            },

            {
                "BlockType": "MoveActor",
                "WaitToFinish": false,
                "TargetActorId": "BanditArmored_3",
                "PathMarkerName": "Band3_3",
                "FollowActor": false,
                "SpeedScale": 1.4
            },
            {
                "BlockType": "MoveActor",
                "WaitToFinish": false,
                "TargetActorId": "BanditCaptain",
                "PathMarkerName": "Cpt3",
                "FollowActor": false,
                "SpeedScale": 1.4
            },
			{
				"BlockType": "SpeechBox",
				"WaitToFinish": true,
				"WaitForNextButton": false,
				"TopBox": true,
				"Entries": [ 
                    {
                        "EntryType": "Clear",
                        "ClearSpeaker": false
                    },
					{
						"EntryType": "Speaker",
						"SpeakerName": "BCpt",
						"SpeakerPort": "res://defs/Actors/NPCs/Bandits/Sprites/Portraits/BanditCpt_Neutral.png"
					},
					{
						"EntryType": "Text",
						"Text": "Check the last of those crates, then we're moving out!",
						"NewLine": true
					},
					{
						"EntryType":"WaitToRead"
					}
				]
            },
            {
                "BlockType": "MoveActor",
                "WaitToFinish": false,
                "StopLoopingActors": ["BanditArcher_1","BanditArcher_2","BanditArmored_1"]
            },
            {

				"BlockType": "SpeechBox",
				"WaitToFinish": false,
				"WaitForNextButton": false,
				"TopBox": true,
				"Entries": [
					{
						"EntryType": "Speaker",
						"SpeakerName": "BCpt",
						"SpeakerPort": "res://defs/Actors/NPCs/Bandits/Sprites/Portraits/BanditCpt_Happy.png"
					},
					{
						"EntryType": "Text",
						"Text": "We got real lucky, @Color:Red@Gang@Clear@. ",
						"NewLine": true
					},
					{
						"EntryType":"WaitToRead"
					},
					{
						"EntryType": "Text",
						"Text": "Abandoned @Color:Red@Merchant Carts@Clear@ aren't something you find everyday, so appreciate the easy @Color:Red@Loot@Clear@.",
						"NewLine": false
					},
					{
						"EntryType":"WaitToRead"
					}
				]
            },
            {
                "BlockType": "MoveActor",
                "WaitToFinish": true,
                "TargetActorId": "BanditArmored_2",
                "PathMarkerName": "Band2_2",
                "FollowActor": false,
                "SpeedScale": 1.2
            },
			{
				"WaitToFinish": false,
				"WaitForNextButton": false,
				"BlockType": "PanCamera",
				"TargetType": "PathMarker",
				"PathMarkerName": "C2"
			},
			{
				"BlockType": "PopUp",
				"WaitToFinish": true,
				"Create":"PopUp1",
				"PopUpType": "SpeechBubble",
				"TargetActorId": "BanditArmored_2",
				"GrowDirection": "Center",
				"Text":"?",
				"Offset": [0,-21]
			},
            {

				"BlockType": "SpeechBox",
				"WaitToFinish": false,
				"WaitForNextButton": false,
				"TopBox": true,
                "Hide": true,
				"Entries": [
					{
						"EntryType":"Clear"
					}
				]
            },
			{
				"BlockType":"Delay",
				"Time": 1
			},
            {
                "BlockType": "MoveActor",
                "WaitToFinish": false,
                "TargetActorId": "BanditArmored_2",
                "PathMarkerName": "Band2_3",
                "FollowActor": false,
                "SpeedScale": 1.2
            },
			{
				"BlockType": "PopUp",
				"WaitToFinish": false,
				"Delete":"PopUp1"
			},
			{
				"BlockType": "SpeechBox",
				"WaitToFinish": true,
				"WaitForNextButton": false,
				"TopBox": false,
				"Entries": [ 
                    {
                        "EntryType": "Clear",
                        "ClearSpeaker": false
                    },
					{
						"EntryType": "Speaker",
						"SpeakerName": "Bndt",
						"SpeakerPort": "res://defs/Actors/NPCs/Bandits/Sprites/Portraits/Bandit_Neutral.png"
					},
                    
					{
						"EntryType": "Text",
						"Text": "... ",
						"LetterDelay": 0.1
					},
					{
						"EntryType": "Text",
						"Text": "Uhh @Color:Red@Captain@Clear@, ",
						"NewLine": false
					},
					{
						"EntryType":"WaitToRead"
					},
					{
						"EntryType": "Text",
						"Text": "we've got a @Color:Red@Soldier@Clear@ here and",
						"NewLine": false
					}
				]
            },
            {
                "BlockType": "MoveActor",
                "WaitToFinish": false,
                "TargetActorId": "BanditArcher_1",
                "PathMarkerName": "Arch1_South",
                "FollowActor": false,
                "SpeedScale": 1
            },
            {
                "BlockType": "MoveActor",
                "WaitToFinish": false,
                "TargetActorId": "BanditArcher_2",
                "PathMarkerName": "Arch2_South",
                "FollowActor": false,
                "SpeedScale": 1
            },
            {
                "BlockType": "MoveActor",
                "WaitToFinish": false,
                "TargetActorId": "BanditArmored_1",
                "PathMarkerName": "Band1_South",
                "FollowActor": false,
                "SpeedScale": 1
            },
			{
				"BlockType": "SpeechBox",
				"WaitToFinish": true,
				"WaitForNextButton": false,
				"TopBox": false,
				"Entries": [ 
                    
					{
						"EntryType": "Text",
						"Text": "... ",
						"LetterDelay": 0.1
					},
					{
						"EntryType": "Text",
						"Text": "some kind of @Color:Red@Demon Monkey@Clear@?",
						"NewLine": true
					}
				]
            }
            
		]
	},
    
	"Dialog2":{
		"_NextPartKey": "CombatStart",
		"WaitForNextButton": false,
		"Inital_BlackOutState": "Clear",
		"EnsurePoses": {
			"_Camera":"C2",
			"Player1":"P1",
			"MysteriousFigure":"M1",
            "BanditArcher_1": "Arch1_South",
            "BanditArcher_2": "Arch2_South",
            "BanditArmored_1": "Band1_South",
            "BanditArmored_2": "Band2_3",
            "BanditArmored_3": "Band3_3",
            "BanditCaptain": "Cpt3"
		},
		"Blocks":[
			{
				"BlockType": "SpeechBox",
				"WaitToFinish": true,
				"WaitForNextButton": false,
				"Entries": [ 
                    {
                        "EntryType": "Clear",
						"ClearSpeaker": false
                    },
					{
						"EntryType": "Speaker",
						"SpeakerName": "MtFr",
						"SpeakerPort": "res://defs/Actors/NPCs/MnFg/Sprites/Portraits/MysFig_Angry.png"
					},
					{
						"EntryType": "Text",
						"Text": "Hey! "
					},
					{
						"EntryType":"WaitToRead"
					},
					{
						"EntryType": "Text",
						"Text": "I'm not a @Color:Red@Monkey@Clear@!"
					},
					{
						"EntryType":"WaitToRead"
					}
                ]
            },
            {
                "BlockType":"Delay",
                "Time":1
            },
			{
				"BlockType": "SpeechBox",
				"WaitToFinish": true,
				"WaitForNextButton": true,
				"TopBox": false,
				"Entries": [ 
                    {
                        "EntryType": "Clear",
                        "ClearSpeaker": false
                    },
					{
						"EntryType": "Speaker",
						"SpeakerName": "BCpt",
						"SpeakerPort": "res://defs/Actors/NPCs/Bandits/Sprites/Portraits/BanditCpt_Laugh.png"
					},
					{
						"EntryType": "Text",
						"Text": "Ha ",
						"NewLine": false
					},
					{
						"EntryType":"Delay",
                        "Delay":0.3
					},
					{
						"EntryType": "Text",
						"Text": "ha ",
						"NewLine": false
					},
					{
						"EntryType":"Delay",
                        "Delay":0.3
					},
					{
						"EntryType": "Text",
						"Text": "ha ",
						"NewLine": false
					},
					{
						"EntryType":"Delay",
                        "Delay":0.3
					},
					{
						"EntryType": "Speaker",
						"SpeakerName": "BCpt",
						"SpeakerPort": "res://defs/Actors/NPCs/Bandits/Sprites/Portraits/BanditCpt_Happy.png"
					},
					{
						"EntryType": "Text",
						"Text": "'course you ain't a @Color:Red@Monkey@Clear@, ",
						"NewLine": false
					},
					{
						"EntryType":"Delay",
                        "Delay":0.8
					},
					{
						"EntryType": "Speaker",
						"SpeakerName": "BCpt",
						"SpeakerPort": "res://defs/Actors/NPCs/Bandits/Sprites/Portraits/BanditCpt_Neutral.png"
					},
					{
						"EntryType": "Text",
						"Text": "you're a witness. ",
						"NewLine": false
					},
					{
						"EntryType":"Delay",
                        "Delay":1
					},
					{
						"EntryType": "Speaker",
						"SpeakerName": "BCpt",
						"SpeakerPort": "res://defs/Actors/NPCs/Bandits/Sprites/Portraits/BanditCpt_Angry.png"
					},
					{
						"EntryType": "Text",
						"Text": "And that's a problem.",
						"NewLine": true
					},
					{
						"EntryType":"WaitToRead"
					}
				]
            },
			{
				"BlockType": "SpeechBox",
				"WaitToFinish": true,
				"WaitForNextButton": false,
				"TopBox": true,
                "Hide": true,
				"Entries": [ 
                    {
                        "EntryType": "Clear",
                        "ClearSpeaker": false
                    }
				]
            },
			{
				"BlockType": "PopUp",
				"WaitToFinish": false,
				"Create":"PopUp2",
				"PopUpType": "SpeechBubble",
				"TargetActorId": "BanditArmored_3",
				"GrowDirection": "Center",
				"Text":"!",
				"Offset": [0,-21]
			},
			{
				"BlockType": "AnimateNode",
                "TargetElement": "MapController/ActorTileMapLayer/RogueInABox",
                "AnimationName": "open_box",
                "WaitToFinish": true
            },
			{
				"BlockType": "PopUp",
				"WaitToFinish": false,
				"Delete":"PopUp2"
			},
            {
                "BlockType": "MoveActor",
                "WaitToFinish": false,
                "TargetActorId": "BanditCaptain",
                "PathMarkerName": "Cpt_Look",
                "FollowActor": false,
                "SpeedScale": 1
            },
			{
				"BlockType": "SpeechBox",
				"WaitToFinish": true,
				"WaitForNextButton": true,
				"TopBox": false,
				"Entries": [ 
                    {
                        "EntryType": "Clear",
                        "ClearSpeaker": false
                    },
					{
						"EntryType": "Speaker",
						"SpeakerName": "BCpt",
						"SpeakerPort": "res://defs/Actors/NPCs/Bandits/Sprites/Portraits/BanditCpt_Angry.png"
					},
					{
						"EntryType": "Text",
						"Text": "Looks like you're not the only ones either.",
						"NewLine": false
					},
					{
						"EntryType":"WaitToRead"
					},
					{
						"EntryType": "Speaker",
						"SpeakerName": "BCpt",
						"SpeakerPort": "res://defs/Actors/NPCs/Bandits/Sprites/Portraits/BanditCpt_Neutral.png"
					},
					{
						"EntryType": "Text",
						"Text": "Don't know you were doing in that box, @Color:Red@Rogue@Clear@.",
						"NewLine": true
					},
					{
						"EntryType":"WaitToRead"
					},
					{
						"EntryType": "Text",
						"Text": "But this @Color:Red@Loot@Clear@'s our, and you three ain't leaving.",
						"NewLine": true
					},
					{
						"EntryType":"WaitToRead"
					}
				]
            },
			{
				"BlockType": "SpeechBox",
				"WaitToFinish": true,
				"WaitForNextButton": true,
				"TopBox": false,
				"Entries": [ 
                    {
                        "EntryType": "Clear",
                        "ClearSpeaker": false
                    },
					{
						"EntryType": "Speaker",
						"SpeakerName": "MtFr",
						"SpeakerPort": "res://defs/Actors/NPCs/MnFg/Sprites/Portraits/MysFig_Neutral.png"
					},
					{
						"EntryType": "Text",
						"Text": "This might actually be a good opertunity for us.",
						"NewLine": false
					},
					{
						"EntryType":"WaitToRead"
					},
					{
						"EntryType": "Speaker",
						"SpeakerName": "MtFr",
						"SpeakerPort": "res://defs/Actors/NPCs/MnFg/Sprites/Portraits/MysFig_Happy.png"
					},
					{
						"EntryType": "Text",
						"Text": "The @Color:Red@Enemy@Clear@ of my @Color:Red@Enemy@Clear@ is a new recruit, as they say.",
						"NewLine": true
					},
					{
						"EntryType":"WaitToRead"
					},
					{
						"EntryType": "Speaker",
						"SpeakerName": "MtFr",
						"SpeakerPort": "res://defs/Actors/NPCs/MnFg/Sprites/Portraits/MysFig_Sad.png"
					},
					{
						"EntryType": "Text",
						"Text": "And we could definitely use the help.",
						"NewLine": true
					},
					{
						"EntryType":"WaitToRead"
					}
				]
            },
			{
				"BlockType": "SpeechBox",
				"WaitToFinish": true,
				"WaitForNextButton": false,
				"TopBox": false,
				"Entries": [ 
                    {
                        "EntryType": "Clear",
                        "ClearSpeaker": false
                    },
					{
						"EntryType": "Speaker",
						"SpeakerName": "MtFr",
						"SpeakerPort": "res://defs/Actors/NPCs/MnFg/Sprites/Portraits/MysFig_Smile.png"
					},
					{
						"EntryType": "Text",
						"Text": "Hey green guy! ",
						"NewLine": false
					},
					{
						"EntryType":"WaitToRead"
					}
				]
            },
			{
				"BlockType": "PopUp",
				"WaitToFinish": true,
				"Create":"PopUp3",
				"PopUpType": "SpeechBubble",
				"TargetActorId": "BanditArmored_3",
				"GrowDirection": "Center",
				"Text":"?",
				"Offset": [32,-21]
			},
			{
				"WaitToFinish": true,
				"WaitForNextButton": false,
				"BlockType": "PanCamera",
				"TargetType": "PathMarker",
				"PathMarkerName": "C3"
			},
			{
				"BlockType": "AnimateNode",
                "TargetElement": "MapController/ActorTileMapLayer/RogueInABox",
                "AnimationName": "look_forward",
                "WaitToFinish": true
            },
            {
                "BlockType": "MoveActor",
                "WaitToFinish": false,
                "TargetActorId": "BanditArcher_1",
                "PathMarkerName": "Arch1_South",
                "FollowActor": false,
                "SpeedScale": 1
            },
            {
                "BlockType": "MoveActor",
                "WaitToFinish": false,
                "TargetActorId": "BanditArcher_2",
                "PathMarkerName": "Arch2_South",
                "FollowActor": false,
                "SpeedScale": 1
            },
            {
                "BlockType": "MoveActor",
                "WaitToFinish": false,
                "TargetActorId": "BanditArmored_1",
                "PathMarkerName": "Band1_South",
                "FollowActor": false,
                "SpeedScale": 1
            },
            {
                "BlockType": "MoveActor",
                "WaitToFinish": false,
                "TargetActorId": "BanditArmored_2",
                "PathMarkerName": "Band2_South",
                "FollowActor": false,
                "SpeedScale": 1
            },
            {
                "BlockType": "MoveActor",
                "WaitToFinish": false,
                "TargetActorId": "BanditArmored_3",
                "PathMarkerName": "Band3_South",
                "FollowActor": false,
                "SpeedScale": 1
            },
            {
                "BlockType": "MoveActor",
                "WaitToFinish": false,
                "TargetActorId": "BanditCaptain",
                "PathMarkerName": "Cpt_South",
                "FollowActor": false,
                "SpeedScale": 1
            },
            {
                "BlockType":"Delay",
                "Time": 0.8
            },
			{
				"BlockType": "PopUp",
				"WaitToFinish": false,
				"Delete":"PopUp3"
			},
			{
				"BlockType": "SpeechBox",
				"WaitToFinish": true,
				"WaitForNextButton": true,
				"TopBox": false,
				"Entries": [ 
					{
						"EntryType": "Speaker",
						"SpeakerName": "MtFr",
						"SpeakerPort": "res://defs/Actors/NPCs/MnFg/Sprites/Portraits/MysFig_Smile.png"
					},
					{
						"EntryType": "Text",
						"Text": "Do you want to be a @Color:Red@Hero@Clear@?",
						"NewLine": true
					},
					{
						"EntryType":"WaitToRead"
					}
				]
            },
			{
				"BlockType": "AnimateNode",
                "TargetElement": "MapController/ActorTileMapLayer/RogueInABox",
                "AnimationName": "look_left",
                "WaitToFinish": true
            },
            {
                "BlockType":"Delay",
                "Time": 0.5
            },
            {
                "BlockType": "MoveActor",
                "WaitToFinish": false,
                "TargetActorId": "BanditArcher_1",
                "PathMarkerName": "Arch1_Look",
                "FollowActor": false,
                "SpeedScale": 1
            },
            {
                "BlockType": "MoveActor",
                "WaitToFinish": false,
                "TargetActorId": "BanditArcher_2",
                "PathMarkerName": "Arch2_Look",
                "FollowActor": false,
                "SpeedScale": 1
            },
            {
                "BlockType": "MoveActor",
                "WaitToFinish": false,
                "TargetActorId": "BanditArmored_1",
                "PathMarkerName": "Band1_Look",
                "FollowActor": false,
                "SpeedScale": 1
            },
            {
                "BlockType": "MoveActor",
                "WaitToFinish": false,
                "TargetActorId": "BanditArmored_2",
                "PathMarkerName": "Band2_Look",
                "FollowActor": false,
                "SpeedScale": 1
            },
            {
                "BlockType": "MoveActor",
                "WaitToFinish": false,
                "TargetActorId": "BanditArmored_3",
                "PathMarkerName": "Band3_Look",
                "FollowActor": false,
                "SpeedScale": 1
            },
            {
                "BlockType": "MoveActor",
                "WaitToFinish": false,
                "TargetActorId": "BanditCaptain",
                "PathMarkerName": "Cpt_Look",
                "FollowActor": false,
                "SpeedScale": 1
            },
            {
                "BlockType":"Delay",
                "Time": 1.5
            },
			{
				"BlockType": "AnimateNode",
                "TargetElement": "MapController/ActorTileMapLayer/RogueInABox",
                "AnimationName": "look_forward",
                "WaitToFinish": true
            },
            {
                "BlockType":"Delay",
                "Time": 0.5
            },
            {
                "BlockType": "MoveActor",
                "WaitToFinish": false,
                "TargetActorId": "BanditArcher_1",
                "PathMarkerName": "Arch1_South",
                "FollowActor": false,
                "SpeedScale": 1
            },
            {
                "BlockType": "MoveActor",
                "WaitToFinish": false,
                "TargetActorId": "BanditArcher_2",
                "PathMarkerName": "Arch2_South",
                "FollowActor": false,
                "SpeedScale": 1
            },
            {
                "BlockType": "MoveActor",
                "WaitToFinish": false,
                "TargetActorId": "BanditArmored_1",
                "PathMarkerName": "Band1_South",
                "FollowActor": false,
                "SpeedScale": 1
            },
            {
                "BlockType": "MoveActor",
                "WaitToFinish": false,
                "TargetActorId": "BanditArmored_2",
                "PathMarkerName": "Band2_3",
                "FollowActor": false,
                "SpeedScale": 1
            },
            {
                "BlockType": "MoveActor",
                "WaitToFinish": false,
                "TargetActorId": "BanditArmored_3",
                "PathMarkerName": "Band3_South",
                "FollowActor": false,
                "SpeedScale": 1
            },
            {
                "BlockType": "MoveActor",
                "WaitToFinish": false,
                "TargetActorId": "BanditCaptain",
                "PathMarkerName": "Cpt_South",
                "FollowActor": false,
                "SpeedScale": 1
            },
            {
                "BlockType":"Delay",
                "Time": 0.5
            },
			{
				"BlockType": "AnimateNode",
                "TargetElement": "MapController/ActorTileMapLayer/RogueInABox",
                "AnimationName": "shake_no",
                "WaitToFinish": true
            },
            {
                "BlockType":"Delay",
                "Time": 1
            },
			{
				"BlockType": "SpeechBox",
				"WaitToFinish": true,
				"WaitForNextButton": true,
				"TopBox": false,
				"Entries": [ 
                    {
                        "EntryType": "Clear",
                        "ClearSpeaker":false

                    },
					{
						"EntryType": "Speaker",
						"SpeakerName": "MtFr",
						"SpeakerPort": "res://defs/Actors/NPCs/MnFg/Sprites/Portraits/MysFig_Neutral.png"
					},
					{
						"EntryType": "Text",
						"Text": "No",
						"NewLine": true
					},
					{
						"EntryType": "Text",
						"Text": "... ",
						"LetterDelay": 0.03
					},
					{
						"EntryType": "Text",
						"Text": "I meant do you want to join @Color:Blue@The Party@Clear@.",
						"NewLine": false
					},
					{
						"EntryType":"WaitToRead"
					},
					{
						"EntryType": "Text",
						"Text": "When @Color:Red@Combat@Clear@ starts you'll @Color:Red@Spawn@Clear@ over here.",
						"NewLine": true
					},
					{
						"EntryType":"WaitToRead"
					}
				]
            },
			{
				"BlockType": "AnimateNode",
                "TargetElement": "MapController/ActorTileMapLayer/RogueInABox",
                "AnimationName": "nod_yes",
                "WaitToFinish": true
            },
			{
				"BlockType": "SpeechBox",
				"WaitToFinish": true,
				"WaitForNextButton": true,
				"TopBox": false,
				"Entries": [ 
                    {
                        "EntryType":"Clear"
                    },
					{
						"EntryType":"Text",
						"Text": "And so, the @Color:Red@Rogue@Clear@ joined the @Color:Blue@The Party@Clear@.",
                        "LetterDelay":0.015
					},
					{
						"EntryType":"WaitToRead"
					}
				]
            },
			{
				"BlockType": "SpeechBox",
				"WaitToFinish": true,
				"WaitForNextButton": true,
				"TopBox": false,
				"Entries": [ 
                    {
                        "EntryType": "Clear",
                        "ClearSpeaker": false
                    },
					{
						"EntryType": "Speaker",
						"SpeakerName": "BCpt",
						"SpeakerPort": "res://defs/Actors/NPCs/Bandits/Sprites/Portraits/BanditCpt_Happy.png"
					},
					{
						"EntryType": "Text",
						"Text": "Good, ",
						"NewLine": false
					},
					{
						"EntryType":"WaitToRead"
					},
					{
						"EntryType": "Text",
						"Text": "now we can make this a proper @Color:Blue@TPK@Clear@.",
						"NewLine": false
					},
					{
						"EntryType":"WaitToRead"
					},
					{
						"EntryType": "Speaker",
						"SpeakerName": "BCpt",
						"SpeakerPort": "res://defs/Actors/NPCs/Bandits/Sprites/Portraits/BanditCpt_Angry.png"
					},
					{
						"EntryType": "Text",
						"Text": "Combat positions, @Color:Red@Gang@Clear@!",
						"NewLine": true
					},
					{
						"EntryType":"WaitToRead"
					}
				]
            },
			{
				"BlockType": "SpeechBox",
				"WaitToFinish": true,
				"WaitForNextButton": false,
				"TopBox": false,
                "Hide": true,
				"Entries": [ 
                    {
                        "EntryType": "Clear"
                    }
				]
            },
            {
                "BlockType":"StartCombat"
            },
			{
				"BlockType": "AnimateNode",
                "TargetElement": "MapController/ActorTileMapLayer/RogueInABox",
                "AnimationName": "HIDE",
                "WaitToFinish": false
            },
			{
				"BlockType":"SpawnActor",
				"SpawnNodeList": ["SpwanNode_Player2"]
			}
        ]
    },
    "CombatStart":{
		"_NextPartLogic": 
		{
			"FlagName": "Tutorial",
			"Cases": {
				"true": "TwoPlayerTutorial",
				"false": "Condition_PlayingCombat"
			}
		},
		"WaitForNextButton": false,
		"Inital_BlackOutState": "Clear",
		"EnsurePoses": {
			"_Camera":"P1",
			"Player1":"P1",
			"Player2":"P2",
			"MysteriousFigure":"Hidden",
            "BanditArcher_1": "BandA1_C",
            "BanditArcher_2": "BandA2_C",
            "BanditArmored_1": "Band1_C",
            "BanditArmored_2": "Band2_C",
            "BanditArmored_3": "Band3_C",
            "BanditCaptain": "BandC_C"
		},
        "Blocks":[
            {
                "BlockType":"StartCombat"
            }
        ]
    },
    "TwoPlayerTutorial":{
		"_NextPartKey": "Condition_PlayingCombat",
		"WaitForNextButton": false,
		"Inital_BlackOutState": "Clear",
		"EnsurePoses": {
			"_Camera":"P1",
			"Player1":"P1",
			"Player2":"P2",
			"MysteriousFigure":"Hidden",
            "BanditArcher_1": "BandA1_C",
            "BanditArcher_2": "BandA2_C",
            "BanditArmored_1": "Band1_C",
            "BanditArmored_2": "Band2_C",
            "BanditArmored_3": "Band3_C",
            "BanditCaptain": "BandC_C"
		},
        "Blocks":[
            {
                "BlockType":"Delay",
                "Time": 3.5
            },
            {   
                "BlockType": "SpeechBox",
                "WaitToFinish": true,
                "WaitForNextButton": true,
                "TopBox": false,
                "Entries": [ 
                    {
                        "EntryType":"Clear",
                        "ClearSpeaker": false
                    },
                    {
                        "EntryType": "Speaker",
                        "SpeakerName": "MtFr",
                        "SpeakerPort": "res://defs/Actors/NPCs/MnFg/Sprites/Portraits/MysFig_Happy.png"
                    },
                    {
                        "EntryType": "Text",
                        "Text": "Now that there are two @Color:Red@Actors@Clear@ on our side, ",
                        "NewLine": false
                    },
                    {
                        "EntryType":"WaitToRead"
                    },
                    {
                        "EntryType": "Text",
                        "Text": "you'll need to plan out both @Color:Blue@ActionQues@Clear@ before you can start the @Color:Red@Round@Clear@.",
                        "NewLine": false
                    },
                    {
                        "EntryType":"WaitToRead"
                    }
                ]
            },
            {   
                "BlockType": "SpeechBox",
                "WaitToFinish": false,
                "WaitForNextButton": false,
                "TopBox": false,
                "Entries": [ 
                    {
                        "EntryType":"Clear",
                        "ClearSpeaker": false
                    },
                    {
                        "EntryType": "Speaker",
                        "SpeakerName": "MtFr",
                        "SpeakerPort": "res://defs/Actors/NPCs/MnFg/Sprites/Portraits/MysFig_Happy.png"
                    },
                    {
                        "EntryType": "Text",
                        "Text": "Click the @Color:Blue@Health Bars@Clear@ at the top of the @Color:Blue@The Screen@Clear@ to switch between @Color:Red@Actors@Clear@.",
                        "NewLine": true
                    },
                    {
                        "EntryType":"WaitToRead"
                    }
                ]
            },
			{
				"BlockType": "PopUp",
				"PopUpType": "Highlight",
				"WaitToFinish": true,
				"Create": "Player2PopUp",
				"TargetElement": "MoveableCamera2D/CanvasLayer/CombatUiControl/StatPanelsContainer/P2_StatPanelControl2/BackPatchContainer",
				"PopupControlSript": "res://Scenes/Dialog/PopUps/OutlinePopUp/outline_pop_up_control.tscn",
				"DarkenScreen": true,
				"Padding":[-8,8,-8,8],
                "LineType":"Dotted",
                "WaitToBeClicked": true,
                "ShowClick": true,
                "Color": [1,1,1,1]
			},
            {   
                "BlockType": "SpeechBox",
                "WaitToFinish": false,
                "WaitForNextButton": false,
                "TopBox": false,
                "Entries": [ 
                    {
                        "EntryType":"Clear",
                        "ClearSpeaker": false
                    },
                    {
                        "EntryType":"Hide"
                    }
                ]
            },
            {
				"BlockType":"CustomBlock",
				"ScriptPath": "res://Scenes/Dialog/CustomDialogBlocks/CampTutorialBlocks.gd",
                "SwitchToPlayer": 1
            },
			{
				"BlockType": "PopUp",
				"PopUpType": "Highlight",
				"WaitToFinish": true,
				"Delete": "Player2PopUp"
			},
            {
                "BlockType":"Delay",
                "Time": 0.3
            },
            {   
                "BlockType": "SpeechBox",
                "WaitToFinish": true,
                "WaitForNextButton": true,
                "TopBox": true,
                "Entries": [ 
                    {
                        "EntryType":"Clear",
                        "ClearSpeaker": false
                    },
                    {
                        "EntryType": "Speaker",
                        "SpeakerName": "MtFr",
                        "SpeakerPort": "res://defs/Actors/NPCs/MnFg/Sprites/Portraits/MysFig_Happy.png"
                    },
                    {
                        "EntryType": "Text",
                        "Text": "As you can see, ",
                        "NewLine": true
                    },
                    {
                        "EntryType":"WaitToRead"
                    },
                    {
                        "EntryType": "Text",
                        "Text": "our new @Color:Red@Rogue@Clear@ came with some @Color:Blue@Pages@Clear@ of thier own.",
                        "NewLine": false
                    },
                    {
                        "EntryType":"WaitToRead"
                    }
                ]
            },
            {   
                "BlockType": "SpeechBox",
                "WaitToFinish": true,
                "WaitForNextButton": true,
                "TopBox": true,
                "Entries": [ 
                    {
                        "EntryType":"Clear",
                        "ClearSpeaker": false
                    },
                    {
                        "EntryType": "Speaker",
                        "SpeakerName": "MtFr",
                        "SpeakerPort": "res://defs/Actors/NPCs/MnFg/Sprites/Portraits/MysFig_Surprize.png"
                    },
                    {
                        "EntryType": "Text",
                        "Text": "Oh! ",
                        "NewLine": true
                    },
                    {
                        "EntryType":"WaitToRead"
                    },
                    {
                        "EntryType": "Speaker",
                        "SpeakerName": "MtFr",
                        "SpeakerPort": "res://defs/Actors/NPCs/MnFg/Sprites/Portraits/MysFig_Happy.png"
                    },
                    {
                        "EntryType": "Text",
                        "Text": " And one of their @Color:Blue@Pages@Clear@ uses @Color:Red@Ammo@Clear@.",
                        "NewLine": false
                    },
                    {
                        "EntryType":"WaitToRead"
                    },
                    {
                        "EntryType": "Text",
                        "Text": "I didn't think I'd get to use the last of my @Color:Red@Flash Cards@Clear@.",
                        "NewLine": true
                    },
                    {
                        "EntryType":"WaitToRead"
                    }
                ]
            },
            {   
                "BlockType": "SpeechBox",
                "WaitToFinish": false,
                "WaitForNextButton": false,
                "TopBox": true,
                "Entries": [ 
                    {
                        "EntryType":"Clear",
                        "ClearSpeaker": false
                    },
                    {
                        "EntryType":"Hide"
                    }
                ]
            },
			{
				"BlockType": "PopUp",
				"WaitToFinish": true,
				"Create": "TutorialCards_1",
				"PopUpType":"TutorialCard",
				"Cards": ["Page Que","Movement","Targeting Actors","Targeting Spots", "Items", "Items 2", "Turns and Gaps","Turn Order","Crashing","Armor and Damage", "Block and Evade", "Page Ammo"],
				"Index": 11
			},
			{
				"WaitToFinish": false,
				"WaitForNextButton": false,
				"BlockType": "PanCamera",
				"TargetType": "PathMarker",
				"PathMarkerName": "BandC_C"
			},
            {   
                "BlockType": "SpeechBox",
                "WaitToFinish": true,
                "WaitForNextButton": true,
                "TopBox": true,
                "Entries": [ 
                    {
                        "EntryType":"Clear",
                        "ClearSpeaker": false
                    },
                    {
                        "EntryType": "Speaker",
                        "SpeakerName": "MtFr",
                        "SpeakerPort": "res://defs/Actors/NPCs/MnFg/Sprites/Portraits/MysFig_Neutral.png"
                    },
                    {
                        "EntryType": "Text",
                        "Text": "I should probably also call out that the  @Color:Red@Bandit Captian@Clear@ is using a @Color:Red@Two-Handed Weapon@Clear@. ",
                        "NewLine": true
                    },
                    {
                        "EntryType":"WaitToRead"
                    },
                    {
                        "EntryType": "Text",
                        "Text": "That means they hit harder, ",
                        "NewLine": false
                    },
                    {
                        "EntryType":"WaitToRead"
                    },
                    {
                        "EntryType": "Text",
                        "Text": "but also thier @Color:Red@Target Area@Clear@ will reach a little further.",
                        "NewLine": false
                    },
                    {
                        "EntryType":"WaitToRead"
                    },
                    {
                        "EntryType": "Speaker",
                        "SpeakerName": "MtFr",
                        "SpeakerPort": "res://defs/Actors/NPCs/MnFg/Sprites/Portraits/MysFig_Happy.png"
                    },
                    {
                        "EntryType": "Text",
                        "Text": "And you know I got a @Color:Red@Flash Card@Clear@ for that too.",
                        "NewLine": true
                    },
                    {
                        "EntryType":"WaitToRead"
                    }
                ]
            },
            {   
                "BlockType": "SpeechBox",
                "WaitToFinish": false,
                "WaitForNextButton": false,
                "TopBox": true,
				"Hide": true,
                "Entries": [ 
                    {
                        "EntryType":"Clear",
                        "ClearSpeaker": false
                    },
                    {
                        "EntryType": "Speaker",
                        "SpeakerName": "MtFr",
                        "SpeakerPort": "res://defs/Actors/NPCs/MnFg/Sprites/Portraits/MysFig_Neutral.png"
                    }
                ]
            },
			{
				"BlockType": "PopUp",
				"WaitToFinish": true,
				"Create": "TutorialCards_1",
				"PopUpType":"TutorialCard",
				"Cards": ["Page Que","Movement","Targeting Actors","Targeting Spots", "Items", "Items 2", "Turns and Gaps","Turn Order","Crashing","Armor and Damage", "Block and Evade", "Page Ammo", "Weapons"],
				"Index": 12
			},
			{
				"WaitToFinish": true,
				"WaitForNextButton": false,
				"BlockType": "PanCamera",
				"TargetType": "PathMarker",
				"PathMarkerName": "P2"
			},
            {   
                "BlockType": "SpeechBox",
                "WaitToFinish": true,
                "WaitForNextButton": true,
                "TopBox": false,
                "Entries": [ 
                    {
                        "EntryType":"Clear",
                        "ClearSpeaker": false
                    },
                    {
                        "EntryType": "Speaker",
                        "SpeakerName": "MtFr",
                        "SpeakerPort": "res://defs/Actors/NPCs/MnFg/Sprites/Portraits/MysFig_Happy.png"
                    },
                    {
                        "EntryType": "Text",
                        "Text": "Good luck @Color:Red@Heros@Clear@!",
                        "NewLine": true
                    },
                    {
                        "EntryType":"WaitToRead"
                    }
                ]
            },
            {   
                "BlockType": "SpeechBox",
                "WaitToFinish": false,
                "WaitForNextButton": false,
                "TopBox": false,
                "Entries": [ 
                    {
                        "EntryType":"Clear",
                        "ClearSpeaker": false
                    },
                    {
                        "EntryType":"Hide"
                    }
                ]
            }
        ]
    },
	"Condition_PlayingCombat":
	{
		"_NextPartKey": "EndBlock",
		"WaitForNextButton": false,
		"Inital_BlackOutState": "Clear",
		"AllowInputThrough": true,
		"HideDialogUI": true,
		"ConditionWatcherScript": "res://Scenes/Dialog/DialogConditionWatchers/DialogCondition_WaitForCombat.gd",
		"IgnoreEnemieIds": [],
		"ShowVictoryScreenOnFinish": true

	},
	"EndBlock": {
		"_NextPartKey": null,
		"WaitForNextButton": false,
		"Inital_BlackOutState": "Clear",
		"AllowInputThrough": true,
		"HideDialogUI": true,
		"OnSkip":{
			"CanSkip":false
		},
		"EnsurePoses": {
		},
		"Blocks":[
			{
				"BlockType": "SetFlag",
				"IsStoryFlag": true,
				"FlagName": "CampLocation",
				"Value": "The Crossroad"
			}
		]
	}
}